{
  "categorys": [
    {
      "name": "甜品",
      "list": [
        {
          "canBook": true,
          "classifyId": 70,
          "code": "0090645a-2ca6-4a5b-b250-13a8403930d5",
          "creatPeriod": "40",
          "createTime": 1505439759644,
          "creatorId": -1,
          "defaultEntity": false,
          "description":
            "慕斯蛋糕是一种以慕斯粉为主材料的糕点。外型、色泽、结构、口味变化丰富，更加自然纯正，通常是加入奶油与凝固剂来制作成浓稠冻状的效果。",
          "id": 71,
          "imageSliderUrl":
            "https://ss3.bdstatic.com/70cFv8Sh_Q1YnxGkpoWK1HF6hhy/it/u=1092526953,1928940804&fm=27&gp=0.jpg",
          "imageUrl":
            "https://ss3.bdstatic.com/70cFv8Sh_Q1YnxGkpoWK1HF6hhy/it/u=1092526953,1928940804&fm=27&gp=0.jpg",
          "memberPrice": 45,
          "name": "慕斯蛋糕",
          "objClass": "com.xdt.ums.shop.common.entity.ProductImpl",
          "price": 50,
          "slider": true
        },
        {
          "canBook": true,
          "classifyId": 70,
          "code": "0090645a-2ca6-4a5b-b250-13a8403930d6",
          "creatPeriod": "40",
          "createTime": 1505439759644,
          "creatorId": -1,
          "defaultEntity": false,
          "description":
            "利用一些鲜水果或者一些果酱、果汁、果粒果酱为主要原材料制作而成的一种水果口味的穆斯。一般情况下草莓、芒果、猕猴桃、香蕉、水蜜桃这几种软质水果用得比较多。",
          "id": 71,
          "imageSliderUrl":
            "https://ss1.bdstatic.com/70cFvXSh_Q1YnxGkpoWK1HF6hhy/it/u=3308833246,2853918385&fm=27&gp=0.jpg",
          "imageUrl":
            "https://ss1.bdstatic.com/70cFvXSh_Q1YnxGkpoWK1HF6hhy/it/u=3308833246,2853918385&fm=27&gp=0.jpg",
          "memberPrice": 35,
          "name": "水果蛋糕",
          "objClass": "com.xdt.ums.shop.common.entity.ProductImpl",
          "price": 70,
          "slider": true
        }
      ]
    },
    {
      "name": "咖啡",
      "list": [
        {
          "canBook": false,
          "classifyId": 62,
          "code": "5cf0fd83-4a3d-4014-9a66-745fdf80222c",
          "creatPeriod": "34",
          "createTime": 1505439679696,
          "creatorId": -1,
          "defaultEntity": false,
          "description":
            "拿铁咖啡是意大利浓缩咖啡(Espresso)与牛奶的经典混合，意大利人也很喜欢把拿铁作为早餐的饮料。意大利人早晨的厨房里，照得到阳光的炉子上通常会同时煮着咖啡和牛奶。",
          "id": 67,
          "imageSliderUrl":
            "https://ss3.bdstatic.com/70cFv8Sh_Q1YnxGkpoWK1HF6hhy/it/u=2730258368,142120483&fm=27&gp=0.jpg",
          "imageUrl":
            "https://ss3.bdstatic.com/70cFv8Sh_Q1YnxGkpoWK1HF6hhy/it/u=2730258368,142120483&fm=27&gp=0.jpg",
          "memberPrice": 8,
          "name": "拿铁咖啡",
          "objClass": "com.xdt.ums.shop.common.entity.ProductImpl",
          "price": 10,
          "slider": true
        },
        {
          "canBook": true,
          "classifyId": 62,
          "code": "73dde60a-a030-4913-af8f-40e8c3403860",
          "creatPeriod": "67",
          "createTime": 1505439688471,
          "creatorId": -1,
          "defaultEntity": false,
          "description":
            "麝香猫咖啡（Kopi Luwak），又称猫屎咖啡，它是由麝香猫在吃完咖啡果后把咖啡豆原封不动的排出，人们把它的粪便中的咖啡豆提取出来后进行加工而成。",
          "id": 69,
          "imageSliderUrl":
            "https://ss3.bdstatic.com/70cFv8Sh_Q1YnxGkpoWK1HF6hhy/it/u=572473064,3340900315&fm=27&gp=0.jpg",
          "imageUrl":
            "https://ss3.bdstatic.com/70cFv8Sh_Q1YnxGkpoWK1HF6hhy/it/u=572473064,3340900315&fm=27&gp=0.jpg",
          "memberPrice": 34,
          "name": "猫屎咖啡",
          "objClass": "com.xdt.ums.shop.common.entity.ProductImpl",
          "price": 45,
          "slider": false
        }
      ]
    },
    {
      "name": "甜品",
      "list": [
        {
          "canBook": true,
          "classifyId": 70,
          "code": "0090645a-2ca6-4a5b-b250-13a8403930d5",
          "creatPeriod": "40",
          "createTime": 1505439759644,
          "creatorId": -1,
          "defaultEntity": false,
          "description":
            "慕斯蛋糕是一种以慕斯粉为主材料的糕点。外型、色泽、结构、口味变化丰富，更加自然纯正，通常是加入奶油与凝固剂来制作成浓稠冻状的效果。",
          "id": 71,
          "imageSliderUrl":
            "https://ss3.bdstatic.com/70cFv8Sh_Q1YnxGkpoWK1HF6hhy/it/u=1092526953,1928940804&fm=27&gp=0.jpg",
          "imageUrl":
            "https://ss3.bdstatic.com/70cFv8Sh_Q1YnxGkpoWK1HF6hhy/it/u=1092526953,1928940804&fm=27&gp=0.jpg",
          "memberPrice": 45,
          "name": "慕斯蛋糕",
          "objClass": "com.xdt.ums.shop.common.entity.ProductImpl",
          "price": 50,
          "slider": true
        },
        {
          "canBook": true,
          "classifyId": 70,
          "code": "0090645a-2ca6-4a5b-b250-13a8403930d6",
          "creatPeriod": "40",
          "createTime": 1505439759644,
          "creatorId": -1,
          "defaultEntity": false,
          "description":
            "利用一些鲜水果或者一些果酱、果汁、果粒果酱为主要原材料制作而成的一种水果口味的穆斯。一般情况下草莓、芒果、猕猴桃、香蕉、水蜜桃这几种软质水果用得比较多。",
          "id": 71,
          "imageSliderUrl":
            "https://ss1.bdstatic.com/70cFvXSh_Q1YnxGkpoWK1HF6hhy/it/u=3308833246,2853918385&fm=27&gp=0.jpg",
          "imageUrl":
            "https://ss1.bdstatic.com/70cFvXSh_Q1YnxGkpoWK1HF6hhy/it/u=3308833246,2853918385&fm=27&gp=0.jpg",
          "memberPrice": 35,
          "name": "水果蛋糕",
          "objClass": "com.xdt.ums.shop.common.entity.ProductImpl",
          "price": 70,
          "slider": true
        }
      ]
    },
    {
      "name": "咖啡",
      "list": [
        {
          "canBook": false,
          "classifyId": 62,
          "code": "5cf0fd83-4a3d-4014-9a66-745fdf80222c",
          "creatPeriod": "34",
          "createTime": 1505439679696,
          "creatorId": -1,
          "defaultEntity": false,
          "description":
            "拿铁咖啡是意大利浓缩咖啡(Espresso)与牛奶的经典混合，意大利人也很喜欢把拿铁作为早餐的饮料。意大利人早晨的厨房里，照得到阳光的炉子上通常会同时煮着咖啡和牛奶。",
          "id": 67,
          "imageSliderUrl":
            "https://ss3.bdstatic.com/70cFv8Sh_Q1YnxGkpoWK1HF6hhy/it/u=2730258368,142120483&fm=27&gp=0.jpg",
          "imageUrl":
            "https://ss3.bdstatic.com/70cFv8Sh_Q1YnxGkpoWK1HF6hhy/it/u=2730258368,142120483&fm=27&gp=0.jpg",
          "memberPrice": 8,
          "name": "拿铁咖啡",
          "objClass": "com.xdt.ums.shop.common.entity.ProductImpl",
          "price": 10,
          "slider": true
        },
        {
          "canBook": true,
          "classifyId": 62,
          "code": "73dde60a-a030-4913-af8f-40e8c3403860",
          "creatPeriod": "67",
          "createTime": 1505439688471,
          "creatorId": -1,
          "defaultEntity": false,
          "description":
            "麝香猫咖啡（Kopi Luwak），又称猫屎咖啡，它是由麝香猫在吃完咖啡果后把咖啡豆原封不动的排出，人们把它的粪便中的咖啡豆提取出来后进行加工而成。",
          "id": 69,
          "imageSliderUrl":
            "https://ss3.bdstatic.com/70cFv8Sh_Q1YnxGkpoWK1HF6hhy/it/u=572473064,3340900315&fm=27&gp=0.jpg",
          "imageUrl":
            "https://ss3.bdstatic.com/70cFv8Sh_Q1YnxGkpoWK1HF6hhy/it/u=572473064,3340900315&fm=27&gp=0.jpg",
          "memberPrice": 34,
          "name": "猫屎咖啡",
          "objClass": "com.xdt.ums.shop.common.entity.ProductImpl",
          "price": 45,
          "slider": false
        }
      ]
    },
    {
      "name": "甜品",
      "list": [
        {
          "canBook": true,
          "classifyId": 70,
          "code": "0090645a-2ca6-4a5b-b250-13a8403930d5",
          "creatPeriod": "40",
          "createTime": 1505439759644,
          "creatorId": -1,
          "defaultEntity": false,
          "description":
            "慕斯蛋糕是一种以慕斯粉为主材料的糕点。外型、色泽、结构、口味变化丰富，更加自然纯正，通常是加入奶油与凝固剂来制作成浓稠冻状的效果。",
          "id": 71,
          "imageSliderUrl":
            "https://ss3.bdstatic.com/70cFv8Sh_Q1YnxGkpoWK1HF6hhy/it/u=1092526953,1928940804&fm=27&gp=0.jpg",
          "imageUrl":
            "https://ss3.bdstatic.com/70cFv8Sh_Q1YnxGkpoWK1HF6hhy/it/u=1092526953,1928940804&fm=27&gp=0.jpg",
          "memberPrice": 45,
          "name": "慕斯蛋糕",
          "objClass": "com.xdt.ums.shop.common.entity.ProductImpl",
          "price": 50,
          "slider": true
        },
        {
          "canBook": true,
          "classifyId": 70,
          "code": "0090645a-2ca6-4a5b-b250-13a8403930d6",
          "creatPeriod": "40",
          "createTime": 1505439759644,
          "creatorId": -1,
          "defaultEntity": false,
          "description":
            "利用一些鲜水果或者一些果酱、果汁、果粒果酱为主要原材料制作而成的一种水果口味的穆斯。一般情况下草莓、芒果、猕猴桃、香蕉、水蜜桃这几种软质水果用得比较多。",
          "id": 71,
          "imageSliderUrl":
            "https://ss1.bdstatic.com/70cFvXSh_Q1YnxGkpoWK1HF6hhy/it/u=3308833246,2853918385&fm=27&gp=0.jpg",
          "imageUrl":
            "https://ss1.bdstatic.com/70cFvXSh_Q1YnxGkpoWK1HF6hhy/it/u=3308833246,2853918385&fm=27&gp=0.jpg",
          "memberPrice": 35,
          "name": "水果蛋糕",
          "objClass": "com.xdt.ums.shop.common.entity.ProductImpl",
          "price": 70,
          "slider": true
        }
      ]
    },
    {
      "name": "咖啡",
      "list": [
        {
          "canBook": false,
          "classifyId": 62,
          "code": "5cf0fd83-4a3d-4014-9a66-745fdf80222c",
          "creatPeriod": "34",
          "createTime": 1505439679696,
          "creatorId": -1,
          "defaultEntity": false,
          "description":
            "拿铁咖啡是意大利浓缩咖啡(Espresso)与牛奶的经典混合，意大利人也很喜欢把拿铁作为早餐的饮料。意大利人早晨的厨房里，照得到阳光的炉子上通常会同时煮着咖啡和牛奶。",
          "id": 67,
          "imageSliderUrl":
            "https://ss3.bdstatic.com/70cFv8Sh_Q1YnxGkpoWK1HF6hhy/it/u=2730258368,142120483&fm=27&gp=0.jpg",
          "imageUrl":
            "https://ss3.bdstatic.com/70cFv8Sh_Q1YnxGkpoWK1HF6hhy/it/u=2730258368,142120483&fm=27&gp=0.jpg",
          "memberPrice": 8,
          "name": "拿铁咖啡",
          "objClass": "com.xdt.ums.shop.common.entity.ProductImpl",
          "price": 10,
          "slider": true
        },
        {
          "canBook": true,
          "classifyId": 62,
          "code": "73dde60a-a030-4913-af8f-40e8c3403860",
          "creatPeriod": "67",
          "createTime": 1505439688471,
          "creatorId": -1,
          "defaultEntity": false,
          "description":
            "麝香猫咖啡（Kopi Luwak），又称猫屎咖啡，它是由麝香猫在吃完咖啡果后把咖啡豆原封不动的排出，人们把它的粪便中的咖啡豆提取出来后进行加工而成。",
          "id": 69,
          "imageSliderUrl":
            "https://ss3.bdstatic.com/70cFv8Sh_Q1YnxGkpoWK1HF6hhy/it/u=572473064,3340900315&fm=27&gp=0.jpg",
          "imageUrl":
            "https://ss3.bdstatic.com/70cFv8Sh_Q1YnxGkpoWK1HF6hhy/it/u=572473064,3340900315&fm=27&gp=0.jpg",
          "memberPrice": 34,
          "name": "猫屎咖啡",
          "objClass": "com.xdt.ums.shop.common.entity.ProductImpl",
          "price": 45,
          "slider": false
        }
      ]
    },
    {
      "name": "甜品",
      "list": [
        {
          "canBook": true,
          "classifyId": 70,
          "code": "0090645a-2ca6-4a5b-b250-13a8403930d5",
          "creatPeriod": "40",
          "createTime": 1505439759644,
          "creatorId": -1,
          "defaultEntity": false,
          "description":
            "慕斯蛋糕是一种以慕斯粉为主材料的糕点。外型、色泽、结构、口味变化丰富，更加自然纯正，通常是加入奶油与凝固剂来制作成浓稠冻状的效果。",
          "id": 71,
          "imageSliderUrl":
            "https://ss3.bdstatic.com/70cFv8Sh_Q1YnxGkpoWK1HF6hhy/it/u=1092526953,1928940804&fm=27&gp=0.jpg",
          "imageUrl":
            "https://ss3.bdstatic.com/70cFv8Sh_Q1YnxGkpoWK1HF6hhy/it/u=1092526953,1928940804&fm=27&gp=0.jpg",
          "memberPrice": 45,
          "name": "慕斯蛋糕",
          "objClass": "com.xdt.ums.shop.common.entity.ProductImpl",
          "price": 50,
          "slider": true
        },
        {
          "canBook": true,
          "classifyId": 70,
          "code": "0090645a-2ca6-4a5b-b250-13a8403930d6",
          "creatPeriod": "40",
          "createTime": 1505439759644,
          "creatorId": -1,
          "defaultEntity": false,
          "description":
            "利用一些鲜水果或者一些果酱、果汁、果粒果酱为主要原材料制作而成的一种水果口味的穆斯。一般情况下草莓、芒果、猕猴桃、香蕉、水蜜桃这几种软质水果用得比较多。",
          "id": 71,
          "imageSliderUrl":
            "https://ss1.bdstatic.com/70cFvXSh_Q1YnxGkpoWK1HF6hhy/it/u=3308833246,2853918385&fm=27&gp=0.jpg",
          "imageUrl":
            "https://ss1.bdstatic.com/70cFvXSh_Q1YnxGkpoWK1HF6hhy/it/u=3308833246,2853918385&fm=27&gp=0.jpg",
          "memberPrice": 35,
          "name": "水果蛋糕",
          "objClass": "com.xdt.ums.shop.common.entity.ProductImpl",
          "price": 70,
          "slider": true
        }
      ]
    },
    {
      "name": "咖啡",
      "list": [
        {
          "canBook": false,
          "classifyId": 62,
          "code": "5cf0fd83-4a3d-4014-9a66-745fdf80222c",
          "creatPeriod": "34",
          "createTime": 1505439679696,
          "creatorId": -1,
          "defaultEntity": false,
          "description":
            "拿铁咖啡是意大利浓缩咖啡(Espresso)与牛奶的经典混合，意大利人也很喜欢把拿铁作为早餐的饮料。意大利人早晨的厨房里，照得到阳光的炉子上通常会同时煮着咖啡和牛奶。",
          "id": 67,
          "imageSliderUrl":
            "https://ss3.bdstatic.com/70cFv8Sh_Q1YnxGkpoWK1HF6hhy/it/u=2730258368,142120483&fm=27&gp=0.jpg",
          "imageUrl":
            "https://ss3.bdstatic.com/70cFv8Sh_Q1YnxGkpoWK1HF6hhy/it/u=2730258368,142120483&fm=27&gp=0.jpg",
          "memberPrice": 8,
          "name": "拿铁咖啡",
          "objClass": "com.xdt.ums.shop.common.entity.ProductImpl",
          "price": 10,
          "slider": true
        },
        {
          "canBook": true,
          "classifyId": 62,
          "code": "73dde60a-a030-4913-af8f-40e8c3403860",
          "creatPeriod": "67",
          "createTime": 1505439688471,
          "creatorId": -1,
          "defaultEntity": false,
          "description":
            "麝香猫咖啡（Kopi Luwak），又称猫屎咖啡，它是由麝香猫在吃完咖啡果后把咖啡豆原封不动的排出，人们把它的粪便中的咖啡豆提取出来后进行加工而成。",
          "id": 69,
          "imageSliderUrl":
            "https://ss3.bdstatic.com/70cFv8Sh_Q1YnxGkpoWK1HF6hhy/it/u=572473064,3340900315&fm=27&gp=0.jpg",
          "imageUrl":
            "https://ss3.bdstatic.com/70cFv8Sh_Q1YnxGkpoWK1HF6hhy/it/u=572473064,3340900315&fm=27&gp=0.jpg",
          "memberPrice": 34,
          "name": "猫屎咖啡",
          "objClass": "com.xdt.ums.shop.common.entity.ProductImpl",
          "price": 45,
          "slider": false
        }
      ]
    },
    {
      "name": "甜品",
      "list": [
        {
          "canBook": true,
          "classifyId": 70,
          "code": "0090645a-2ca6-4a5b-b250-13a8403930d5",
          "creatPeriod": "40",
          "createTime": 1505439759644,
          "creatorId": -1,
          "defaultEntity": false,
          "description":
            "慕斯蛋糕是一种以慕斯粉为主材料的糕点。外型、色泽、结构、口味变化丰富，更加自然纯正，通常是加入奶油与凝固剂来制作成浓稠冻状的效果。",
          "id": 71,
          "imageSliderUrl":
            "https://ss3.bdstatic.com/70cFv8Sh_Q1YnxGkpoWK1HF6hhy/it/u=1092526953,1928940804&fm=27&gp=0.jpg",
          "imageUrl":
            "https://ss3.bdstatic.com/70cFv8Sh_Q1YnxGkpoWK1HF6hhy/it/u=1092526953,1928940804&fm=27&gp=0.jpg",
          "memberPrice": 45,
          "name": "慕斯蛋糕",
          "objClass": "com.xdt.ums.shop.common.entity.ProductImpl",
          "price": 50,
          "slider": true
        },
        {
          "canBook": true,
          "classifyId": 70,
          "code": "0090645a-2ca6-4a5b-b250-13a8403930d6",
          "creatPeriod": "40",
          "createTime": 1505439759644,
          "creatorId": -1,
          "defaultEntity": false,
          "description":
            "利用一些鲜水果或者一些果酱、果汁、果粒果酱为主要原材料制作而成的一种水果口味的穆斯。一般情况下草莓、芒果、猕猴桃、香蕉、水蜜桃这几种软质水果用得比较多。",
          "id": 71,
          "imageSliderUrl":
            "https://ss1.bdstatic.com/70cFvXSh_Q1YnxGkpoWK1HF6hhy/it/u=3308833246,2853918385&fm=27&gp=0.jpg",
          "imageUrl":
            "https://ss1.bdstatic.com/70cFvXSh_Q1YnxGkpoWK1HF6hhy/it/u=3308833246,2853918385&fm=27&gp=0.jpg",
          "memberPrice": 35,
          "name": "水果蛋糕",
          "objClass": "com.xdt.ums.shop.common.entity.ProductImpl",
          "price": 70,
          "slider": true
        }
      ]
    },
    {
      "name": "咖啡",
      "list": [
        {
          "canBook": false,
          "classifyId": 62,
          "code": "5cf0fd83-4a3d-4014-9a66-745fdf80222c",
          "creatPeriod": "34",
          "createTime": 1505439679696,
          "creatorId": -1,
          "defaultEntity": false,
          "description":
            "拿铁咖啡是意大利浓缩咖啡(Espresso)与牛奶的经典混合，意大利人也很喜欢把拿铁作为早餐的饮料。意大利人早晨的厨房里，照得到阳光的炉子上通常会同时煮着咖啡和牛奶。",
          "id": 67,
          "imageSliderUrl":
            "https://ss3.bdstatic.com/70cFv8Sh_Q1YnxGkpoWK1HF6hhy/it/u=2730258368,142120483&fm=27&gp=0.jpg",
          "imageUrl":
            "https://ss3.bdstatic.com/70cFv8Sh_Q1YnxGkpoWK1HF6hhy/it/u=2730258368,142120483&fm=27&gp=0.jpg",
          "memberPrice": 8,
          "name": "拿铁咖啡",
          "objClass": "com.xdt.ums.shop.common.entity.ProductImpl",
          "price": 10,
          "slider": true
        },
        {
          "canBook": true,
          "classifyId": 62,
          "code": "73dde60a-a030-4913-af8f-40e8c3403860",
          "creatPeriod": "67",
          "createTime": 1505439688471,
          "creatorId": -1,
          "defaultEntity": false,
          "description":
            "麝香猫咖啡（Kopi Luwak），又称猫屎咖啡，它是由麝香猫在吃完咖啡果后把咖啡豆原封不动的排出，人们把它的粪便中的咖啡豆提取出来后进行加工而成。",
          "id": 69,
          "imageSliderUrl":
            "https://ss3.bdstatic.com/70cFv8Sh_Q1YnxGkpoWK1HF6hhy/it/u=572473064,3340900315&fm=27&gp=0.jpg",
          "imageUrl":
            "https://ss3.bdstatic.com/70cFv8Sh_Q1YnxGkpoWK1HF6hhy/it/u=572473064,3340900315&fm=27&gp=0.jpg",
          "memberPrice": 34,
          "name": "猫屎咖啡",
          "objClass": "com.xdt.ums.shop.common.entity.ProductImpl",
          "price": 45,
          "slider": false
        }
      ]
    },
    {
      "name": "甜品",
      "list": [
        {
          "canBook": true,
          "classifyId": 70,
          "code": "0090645a-2ca6-4a5b-b250-13a8403930d5",
          "creatPeriod": "40",
          "createTime": 1505439759644,
          "creatorId": -1,
          "defaultEntity": false,
          "description":
            "慕斯蛋糕是一种以慕斯粉为主材料的糕点。外型、色泽、结构、口味变化丰富，更加自然纯正，通常是加入奶油与凝固剂来制作成浓稠冻状的效果。",
          "id": 71,
          "imageSliderUrl":
            "https://ss3.bdstatic.com/70cFv8Sh_Q1YnxGkpoWK1HF6hhy/it/u=1092526953,1928940804&fm=27&gp=0.jpg",
          "imageUrl":
            "https://ss3.bdstatic.com/70cFv8Sh_Q1YnxGkpoWK1HF6hhy/it/u=1092526953,1928940804&fm=27&gp=0.jpg",
          "memberPrice": 45,
          "name": "慕斯蛋糕",
          "objClass": "com.xdt.ums.shop.common.entity.ProductImpl",
          "price": 50,
          "slider": true
        },
        {
          "canBook": true,
          "classifyId": 70,
          "code": "0090645a-2ca6-4a5b-b250-13a8403930d6",
          "creatPeriod": "40",
          "createTime": 1505439759644,
          "creatorId": -1,
          "defaultEntity": false,
          "description":
            "利用一些鲜水果或者一些果酱、果汁、果粒果酱为主要原材料制作而成的一种水果口味的穆斯。一般情况下草莓、芒果、猕猴桃、香蕉、水蜜桃这几种软质水果用得比较多。",
          "id": 71,
          "imageSliderUrl":
            "https://ss1.bdstatic.com/70cFvXSh_Q1YnxGkpoWK1HF6hhy/it/u=3308833246,2853918385&fm=27&gp=0.jpg",
          "imageUrl":
            "https://ss1.bdstatic.com/70cFvXSh_Q1YnxGkpoWK1HF6hhy/it/u=3308833246,2853918385&fm=27&gp=0.jpg",
          "memberPrice": 35,
          "name": "水果蛋糕",
          "objClass": "com.xdt.ums.shop.common.entity.ProductImpl",
          "price": 70,
          "slider": true
        }
      ]
    },
    {
      "name": "咖啡",
      "list": [
        {
          "canBook": false,
          "classifyId": 62,
          "code": "5cf0fd83-4a3d-4014-9a66-745fdf80222c",
          "creatPeriod": "34",
          "createTime": 1505439679696,
          "creatorId": -1,
          "defaultEntity": false,
          "description":
            "拿铁咖啡是意大利浓缩咖啡(Espresso)与牛奶的经典混合，意大利人也很喜欢把拿铁作为早餐的饮料。意大利人早晨的厨房里，照得到阳光的炉子上通常会同时煮着咖啡和牛奶。",
          "id": 67,
          "imageSliderUrl":
            "https://ss3.bdstatic.com/70cFv8Sh_Q1YnxGkpoWK1HF6hhy/it/u=2730258368,142120483&fm=27&gp=0.jpg",
          "imageUrl":
            "https://ss3.bdstatic.com/70cFv8Sh_Q1YnxGkpoWK1HF6hhy/it/u=2730258368,142120483&fm=27&gp=0.jpg",
          "memberPrice": 8,
          "name": "拿铁咖啡",
          "objClass": "com.xdt.ums.shop.common.entity.ProductImpl",
          "price": 10,
          "slider": true
        },
        {
          "canBook": true,
          "classifyId": 62,
          "code": "73dde60a-a030-4913-af8f-40e8c3403860",
          "creatPeriod": "67",
          "createTime": 1505439688471,
          "creatorId": -1,
          "defaultEntity": false,
          "description":
            "麝香猫咖啡（Kopi Luwak），又称猫屎咖啡，它是由麝香猫在吃完咖啡果后把咖啡豆原封不动的排出，人们把它的粪便中的咖啡豆提取出来后进行加工而成。",
          "id": 69,
          "imageSliderUrl":
            "https://ss3.bdstatic.com/70cFv8Sh_Q1YnxGkpoWK1HF6hhy/it/u=572473064,3340900315&fm=27&gp=0.jpg",
          "imageUrl":
            "https://ss3.bdstatic.com/70cFv8Sh_Q1YnxGkpoWK1HF6hhy/it/u=572473064,3340900315&fm=27&gp=0.jpg",
          "memberPrice": 34,
          "name": "猫屎咖啡",
          "objClass": "com.xdt.ums.shop.common.entity.ProductImpl",
          "price": 45,
          "slider": false
        }
      ]
    },
    {
      "name": "甜品",
      "list": [
        {
          "canBook": true,
          "classifyId": 70,
          "code": "0090645a-2ca6-4a5b-b250-13a8403930d5",
          "creatPeriod": "40",
          "createTime": 1505439759644,
          "creatorId": -1,
          "defaultEntity": false,
          "description":
            "慕斯蛋糕是一种以慕斯粉为主材料的糕点。外型、色泽、结构、口味变化丰富，更加自然纯正，通常是加入奶油与凝固剂来制作成浓稠冻状的效果。",
          "id": 71,
          "imageSliderUrl":
            "https://ss3.bdstatic.com/70cFv8Sh_Q1YnxGkpoWK1HF6hhy/it/u=1092526953,1928940804&fm=27&gp=0.jpg",
          "imageUrl":
            "https://ss3.bdstatic.com/70cFv8Sh_Q1YnxGkpoWK1HF6hhy/it/u=1092526953,1928940804&fm=27&gp=0.jpg",
          "memberPrice": 45,
          "name": "慕斯蛋糕",
          "objClass": "com.xdt.ums.shop.common.entity.ProductImpl",
          "price": 50,
          "slider": true
        },
        {
          "canBook": true,
          "classifyId": 70,
          "code": "0090645a-2ca6-4a5b-b250-13a8403930d6",
          "creatPeriod": "40",
          "createTime": 1505439759644,
          "creatorId": -1,
          "defaultEntity": false,
          "description":
            "利用一些鲜水果或者一些果酱、果汁、果粒果酱为主要原材料制作而成的一种水果口味的穆斯。一般情况下草莓、芒果、猕猴桃、香蕉、水蜜桃这几种软质水果用得比较多。",
          "id": 71,
          "imageSliderUrl":
            "https://ss1.bdstatic.com/70cFvXSh_Q1YnxGkpoWK1HF6hhy/it/u=3308833246,2853918385&fm=27&gp=0.jpg",
          "imageUrl":
            "https://ss1.bdstatic.com/70cFvXSh_Q1YnxGkpoWK1HF6hhy/it/u=3308833246,2853918385&fm=27&gp=0.jpg",
          "memberPrice": 35,
          "name": "水果蛋糕",
          "objClass": "com.xdt.ums.shop.common.entity.ProductImpl",
          "price": 70,
          "slider": true
        }
      ]
    },
    {
      "name": "咖啡",
      "list": [
        {
          "canBook": false,
          "classifyId": 62,
          "code": "5cf0fd83-4a3d-4014-9a66-745fdf80222c",
          "creatPeriod": "34",
          "createTime": 1505439679696,
          "creatorId": -1,
          "defaultEntity": false,
          "description":
            "拿铁咖啡是意大利浓缩咖啡(Espresso)与牛奶的经典混合，意大利人也很喜欢把拿铁作为早餐的饮料。意大利人早晨的厨房里，照得到阳光的炉子上通常会同时煮着咖啡和牛奶。",
          "id": 67,
          "imageSliderUrl":
            "https://ss3.bdstatic.com/70cFv8Sh_Q1YnxGkpoWK1HF6hhy/it/u=2730258368,142120483&fm=27&gp=0.jpg",
          "imageUrl":
            "https://ss3.bdstatic.com/70cFv8Sh_Q1YnxGkpoWK1HF6hhy/it/u=2730258368,142120483&fm=27&gp=0.jpg",
          "memberPrice": 8,
          "name": "拿铁咖啡",
          "objClass": "com.xdt.ums.shop.common.entity.ProductImpl",
          "price": 10,
          "slider": true
        },
        {
          "canBook": true,
          "classifyId": 62,
          "code": "73dde60a-a030-4913-af8f-40e8c3403860",
          "creatPeriod": "67",
          "createTime": 1505439688471,
          "creatorId": -1,
          "defaultEntity": false,
          "description":
            "麝香猫咖啡（Kopi Luwak），又称猫屎咖啡，它是由麝香猫在吃完咖啡果后把咖啡豆原封不动的排出，人们把它的粪便中的咖啡豆提取出来后进行加工而成。",
          "id": 69,
          "imageSliderUrl":
            "https://ss3.bdstatic.com/70cFv8Sh_Q1YnxGkpoWK1HF6hhy/it/u=572473064,3340900315&fm=27&gp=0.jpg",
          "imageUrl":
            "https://ss3.bdstatic.com/70cFv8Sh_Q1YnxGkpoWK1HF6hhy/it/u=572473064,3340900315&fm=27&gp=0.jpg",
          "memberPrice": 34,
          "name": "猫屎咖啡",
          "objClass": "com.xdt.ums.shop.common.entity.ProductImpl",
          "price": 45,
          "slider": false
        }
      ]
    },
    {
      "name": "甜品",
      "list": [
        {
          "canBook": true,
          "classifyId": 70,
          "code": "0090645a-2ca6-4a5b-b250-13a8403930d5",
          "creatPeriod": "40",
          "createTime": 1505439759644,
          "creatorId": -1,
          "defaultEntity": false,
          "description":
            "慕斯蛋糕是一种以慕斯粉为主材料的糕点。外型、色泽、结构、口味变化丰富，更加自然纯正，通常是加入奶油与凝固剂来制作成浓稠冻状的效果。",
          "id": 71,
          "imageSliderUrl":
            "https://ss3.bdstatic.com/70cFv8Sh_Q1YnxGkpoWK1HF6hhy/it/u=1092526953,1928940804&fm=27&gp=0.jpg",
          "imageUrl":
            "https://ss3.bdstatic.com/70cFv8Sh_Q1YnxGkpoWK1HF6hhy/it/u=1092526953,1928940804&fm=27&gp=0.jpg",
          "memberPrice": 45,
          "name": "慕斯蛋糕",
          "objClass": "com.xdt.ums.shop.common.entity.ProductImpl",
          "price": 50,
          "slider": true
        },
        {
          "canBook": true,
          "classifyId": 70,
          "code": "0090645a-2ca6-4a5b-b250-13a8403930d6",
          "creatPeriod": "40",
          "createTime": 1505439759644,
          "creatorId": -1,
          "defaultEntity": false,
          "description":
            "利用一些鲜水果或者一些果酱、果汁、果粒果酱为主要原材料制作而成的一种水果口味的穆斯。一般情况下草莓、芒果、猕猴桃、香蕉、水蜜桃这几种软质水果用得比较多。",
          "id": 71,
          "imageSliderUrl":
            "https://ss1.bdstatic.com/70cFvXSh_Q1YnxGkpoWK1HF6hhy/it/u=3308833246,2853918385&fm=27&gp=0.jpg",
          "imageUrl":
            "https://ss1.bdstatic.com/70cFvXSh_Q1YnxGkpoWK1HF6hhy/it/u=3308833246,2853918385&fm=27&gp=0.jpg",
          "memberPrice": 35,
          "name": "水果蛋糕",
          "objClass": "com.xdt.ums.shop.common.entity.ProductImpl",
          "price": 70,
          "slider": true
        }
      ]
    },
    {
      "name": "咖啡",
      "list": [
        {
          "canBook": false,
          "classifyId": 62,
          "code": "5cf0fd83-4a3d-4014-9a66-745fdf80222c",
          "creatPeriod": "34",
          "createTime": 1505439679696,
          "creatorId": -1,
          "defaultEntity": false,
          "description":
            "拿铁咖啡是意大利浓缩咖啡(Espresso)与牛奶的经典混合，意大利人也很喜欢把拿铁作为早餐的饮料。意大利人早晨的厨房里，照得到阳光的炉子上通常会同时煮着咖啡和牛奶。",
          "id": 67,
          "imageSliderUrl":
            "https://ss3.bdstatic.com/70cFv8Sh_Q1YnxGkpoWK1HF6hhy/it/u=2730258368,142120483&fm=27&gp=0.jpg",
          "imageUrl":
            "https://ss3.bdstatic.com/70cFv8Sh_Q1YnxGkpoWK1HF6hhy/it/u=2730258368,142120483&fm=27&gp=0.jpg",
          "memberPrice": 8,
          "name": "拿铁咖啡",
          "objClass": "com.xdt.ums.shop.common.entity.ProductImpl",
          "price": 10,
          "slider": true
        },
        {
          "canBook": true,
          "classifyId": 62,
          "code": "73dde60a-a030-4913-af8f-40e8c3403860",
          "creatPeriod": "67",
          "createTime": 1505439688471,
          "creatorId": -1,
          "defaultEntity": false,
          "description":
            "麝香猫咖啡（Kopi Luwak），又称猫屎咖啡，它是由麝香猫在吃完咖啡果后把咖啡豆原封不动的排出，人们把它的粪便中的咖啡豆提取出来后进行加工而成。",
          "id": 69,
          "imageSliderUrl":
            "https://ss3.bdstatic.com/70cFv8Sh_Q1YnxGkpoWK1HF6hhy/it/u=572473064,3340900315&fm=27&gp=0.jpg",
          "imageUrl":
            "https://ss3.bdstatic.com/70cFv8Sh_Q1YnxGkpoWK1HF6hhy/it/u=572473064,3340900315&fm=27&gp=0.jpg",
          "memberPrice": 34,
          "name": "猫屎咖啡",
          "objClass": "com.xdt.ums.shop.common.entity.ProductImpl",
          "price": 45,
          "slider": false
        }
      ]
    },
    {
      "name": "甜品",
      "list": [
        {
          "canBook": true,
          "classifyId": 70,
          "code": "0090645a-2ca6-4a5b-b250-13a8403930d5",
          "creatPeriod": "40",
          "createTime": 1505439759644,
          "creatorId": -1,
          "defaultEntity": false,
          "description":
            "慕斯蛋糕是一种以慕斯粉为主材料的糕点。外型、色泽、结构、口味变化丰富，更加自然纯正，通常是加入奶油与凝固剂来制作成浓稠冻状的效果。",
          "id": 71,
          "imageSliderUrl":
            "https://ss3.bdstatic.com/70cFv8Sh_Q1YnxGkpoWK1HF6hhy/it/u=1092526953,1928940804&fm=27&gp=0.jpg",
          "imageUrl":
            "https://ss3.bdstatic.com/70cFv8Sh_Q1YnxGkpoWK1HF6hhy/it/u=1092526953,1928940804&fm=27&gp=0.jpg",
          "memberPrice": 45,
          "name": "慕斯蛋糕",
          "objClass": "com.xdt.ums.shop.common.entity.ProductImpl",
          "price": 50,
          "slider": true
        },
        {
          "canBook": true,
          "classifyId": 70,
          "code": "0090645a-2ca6-4a5b-b250-13a8403930d6",
          "creatPeriod": "40",
          "createTime": 1505439759644,
          "creatorId": -1,
          "defaultEntity": false,
          "description":
            "利用一些鲜水果或者一些果酱、果汁、果粒果酱为主要原材料制作而成的一种水果口味的穆斯。一般情况下草莓、芒果、猕猴桃、香蕉、水蜜桃这几种软质水果用得比较多。",
          "id": 71,
          "imageSliderUrl":
            "https://ss1.bdstatic.com/70cFvXSh_Q1YnxGkpoWK1HF6hhy/it/u=3308833246,2853918385&fm=27&gp=0.jpg",
          "imageUrl":
            "https://ss1.bdstatic.com/70cFvXSh_Q1YnxGkpoWK1HF6hhy/it/u=3308833246,2853918385&fm=27&gp=0.jpg",
          "memberPrice": 35,
          "name": "水果蛋糕",
          "objClass": "com.xdt.ums.shop.common.entity.ProductImpl",
          "price": 70,
          "slider": true
        }
      ]
    },
    {
      "name": "咖啡",
      "list": [
        {
          "canBook": false,
          "classifyId": 62,
          "code": "5cf0fd83-4a3d-4014-9a66-745fdf80222c",
          "creatPeriod": "34",
          "createTime": 1505439679696,
          "creatorId": -1,
          "defaultEntity": false,
          "description":
            "拿铁咖啡是意大利浓缩咖啡(Espresso)与牛奶的经典混合，意大利人也很喜欢把拿铁作为早餐的饮料。意大利人早晨的厨房里，照得到阳光的炉子上通常会同时煮着咖啡和牛奶。",
          "id": 67,
          "imageSliderUrl":
            "https://ss3.bdstatic.com/70cFv8Sh_Q1YnxGkpoWK1HF6hhy/it/u=2730258368,142120483&fm=27&gp=0.jpg",
          "imageUrl":
            "https://ss3.bdstatic.com/70cFv8Sh_Q1YnxGkpoWK1HF6hhy/it/u=2730258368,142120483&fm=27&gp=0.jpg",
          "memberPrice": 8,
          "name": "拿铁咖啡",
          "objClass": "com.xdt.ums.shop.common.entity.ProductImpl",
          "price": 10,
          "slider": true
        },
        {
          "canBook": true,
          "classifyId": 62,
          "code": "73dde60a-a030-4913-af8f-40e8c3403860",
          "creatPeriod": "67",
          "createTime": 1505439688471,
          "creatorId": -1,
          "defaultEntity": false,
          "description":
            "麝香猫咖啡（Kopi Luwak），又称猫屎咖啡，它是由麝香猫在吃完咖啡果后把咖啡豆原封不动的排出，人们把它的粪便中的咖啡豆提取出来后进行加工而成。",
          "id": 69,
          "imageSliderUrl":
            "https://ss3.bdstatic.com/70cFv8Sh_Q1YnxGkpoWK1HF6hhy/it/u=572473064,3340900315&fm=27&gp=0.jpg",
          "imageUrl":
            "https://ss3.bdstatic.com/70cFv8Sh_Q1YnxGkpoWK1HF6hhy/it/u=572473064,3340900315&fm=27&gp=0.jpg",
          "memberPrice": 34,
          "name": "猫屎咖啡",
          "objClass": "com.xdt.ums.shop.common.entity.ProductImpl",
          "price": 45,
          "slider": false
        }
      ]
    },
    {
      "name": "甜品",
      "list": [
        {
          "canBook": true,
          "classifyId": 70,
          "code": "0090645a-2ca6-4a5b-b250-13a8403930d5",
          "creatPeriod": "40",
          "createTime": 1505439759644,
          "creatorId": -1,
          "defaultEntity": false,
          "description":
            "慕斯蛋糕是一种以慕斯粉为主材料的糕点。外型、色泽、结构、口味变化丰富，更加自然纯正，通常是加入奶油与凝固剂来制作成浓稠冻状的效果。",
          "id": 71,
          "imageSliderUrl":
            "https://ss3.bdstatic.com/70cFv8Sh_Q1YnxGkpoWK1HF6hhy/it/u=1092526953,1928940804&fm=27&gp=0.jpg",
          "imageUrl":
            "https://ss3.bdstatic.com/70cFv8Sh_Q1YnxGkpoWK1HF6hhy/it/u=1092526953,1928940804&fm=27&gp=0.jpg",
          "memberPrice": 45,
          "name": "慕斯蛋糕",
          "objClass": "com.xdt.ums.shop.common.entity.ProductImpl",
          "price": 50,
          "slider": true
        },
        {
          "canBook": true,
          "classifyId": 70,
          "code": "0090645a-2ca6-4a5b-b250-13a8403930d6",
          "creatPeriod": "40",
          "createTime": 1505439759644,
          "creatorId": -1,
          "defaultEntity": false,
          "description":
            "利用一些鲜水果或者一些果酱、果汁、果粒果酱为主要原材料制作而成的一种水果口味的穆斯。一般情况下草莓、芒果、猕猴桃、香蕉、水蜜桃这几种软质水果用得比较多。",
          "id": 71,
          "imageSliderUrl":
            "https://ss1.bdstatic.com/70cFvXSh_Q1YnxGkpoWK1HF6hhy/it/u=3308833246,2853918385&fm=27&gp=0.jpg",
          "imageUrl":
            "https://ss1.bdstatic.com/70cFvXSh_Q1YnxGkpoWK1HF6hhy/it/u=3308833246,2853918385&fm=27&gp=0.jpg",
          "memberPrice": 35,
          "name": "水果蛋糕",
          "objClass": "com.xdt.ums.shop.common.entity.ProductImpl",
          "price": 70,
          "slider": true
        }
      ]
    },
    {
      "name": "咖啡",
      "list": [
        {
          "canBook": false,
          "classifyId": 62,
          "code": "5cf0fd83-4a3d-4014-9a66-745fdf80222c",
          "creatPeriod": "34",
          "createTime": 1505439679696,
          "creatorId": -1,
          "defaultEntity": false,
          "description":
            "拿铁咖啡是意大利浓缩咖啡(Espresso)与牛奶的经典混合，意大利人也很喜欢把拿铁作为早餐的饮料。意大利人早晨的厨房里，照得到阳光的炉子上通常会同时煮着咖啡和牛奶。",
          "id": 67,
          "imageSliderUrl":
            "https://ss3.bdstatic.com/70cFv8Sh_Q1YnxGkpoWK1HF6hhy/it/u=2730258368,142120483&fm=27&gp=0.jpg",
          "imageUrl":
            "https://ss3.bdstatic.com/70cFv8Sh_Q1YnxGkpoWK1HF6hhy/it/u=2730258368,142120483&fm=27&gp=0.jpg",
          "memberPrice": 8,
          "name": "拿铁咖啡",
          "objClass": "com.xdt.ums.shop.common.entity.ProductImpl",
          "price": 10,
          "slider": true
        },
        {
          "canBook": true,
          "classifyId": 62,
          "code": "73dde60a-a030-4913-af8f-40e8c3403860",
          "creatPeriod": "67",
          "createTime": 1505439688471,
          "creatorId": -1,
          "defaultEntity": false,
          "description":
            "麝香猫咖啡（Kopi Luwak），又称猫屎咖啡，它是由麝香猫在吃完咖啡果后把咖啡豆原封不动的排出，人们把它的粪便中的咖啡豆提取出来后进行加工而成。",
          "id": 69,
          "imageSliderUrl":
            "https://ss3.bdstatic.com/70cFv8Sh_Q1YnxGkpoWK1HF6hhy/it/u=572473064,3340900315&fm=27&gp=0.jpg",
          "imageUrl":
            "https://ss3.bdstatic.com/70cFv8Sh_Q1YnxGkpoWK1HF6hhy/it/u=572473064,3340900315&fm=27&gp=0.jpg",
          "memberPrice": 34,
          "name": "猫屎咖啡",
          "objClass": "com.xdt.ums.shop.common.entity.ProductImpl",
          "price": 45,
          "slider": false
        }
      ]
    }
  ],
  "login": {
    "poor": {
      "status": true,
      "balance": 15,
      "cardGrade": "",
      "cardNo": "",
      "cardStatus": "",
      "createTime": "2017-10-23 21:04:13",
      "description": "",
      "gender": "Male",
      "handNo": "",
      "id": 107,
      "name": "totti"
    },
    "rich": {
      "status": true,
      "balance": 500,
      "cardGrade": "",
      "cardNo": "",
      "cardStatus": "",
      "createTime": "2017-10-23 21:04:13",
      "description": "",
      "gender": "Male",
      "handNo": "",
      "id": 10,
      "name": "david"
    },
    "fail": {
      "status": false
    }
  },
  "register": {
    "poor": {
      "entityId": "3",
      "entityName": "totti",
      "envData": {
        "endRow": -1,
        "language": "",
        "pageNo": -1,
        "pageSize": -1,
        "realTotalRows": -1,
        "responseStatus": "0",
        "startRow": -1,
        "totalPages": -1,
        "totalRows": -1,
        "userIp": "",
        "userName": ""
      },
      "success": true
    },
    "rich": {
      "entityId": "13",
      "entityName": "david",
      "envData": {
        "endRow": -1,
        "language": "",
        "pageNo": -1,
        "pageSize": -1,
        "realTotalRows": -1,
        "responseStatus": "0",
        "startRow": -1,
        "totalPages": -1,
        "totalRows": -1,
        "userIp": "",
        "userName": ""
      },
      "success": true
    },
    "other": {
      "entityId": "888",
      "entityName": "Vue",
      "envData": {
        "endRow": -1,
        "language": "",
        "pageNo": -1,
        "pageSize": -1,
        "realTotalRows": -1,
        "responseStatus": "0",
        "startRow": -1,
        "totalPages": -1,
        "totalRows": -1,
        "userIp": "",
        "userName": ""
      },
      "success": true
    }
  },
  "cartDetailList": [
    {
      "amount": 66,
      "cashOrBanlance": " ",
      "code": "34c9829f-d57d-4e35-a8cb-51b861467b21",
      "createTime": 1508251634463,
      "creatorId": -1,
      "defaultEntity": false,
      "details": [
        {
          "amount": 22,
          "code": "0cf24a6a-d464-4657-806f-412b508c24d1",
          "createTime": 1508251633955,
          "creatorId": -1,
          "defaultEntity": false,
          "id": 100,
          "number": 2,
          "objClass": "com.xdt.ums.shop.common.entity.DetailImpl",
          "price": 11,
          "productName": "慕斯蛋糕",
          "productId": 2,
          "recordId": 99
        },
        {
          "amount": 44,
          "code": "c4abae95-d9d0-408d-8397-57c12fd125c1",
          "createTime": 1508251633955,
          "creatorId": -1,
          "defaultEntity": false,
          "id": 101,
          "number": 2,
          "objClass": "com.xdt.ums.shop.common.entity.DetailImpl",
          "productId": 3,
          "price": 22,
          "productName": "美式咖啡",
          "recordId": 99
        }
      ],
      "id": 99,
      "objClass": "com.xdt.ums.shop.common.entity.RecordImpl",
      "status": "waitpay",
      "userId": 84,
      "userName": "test3"
    },
    {
      "amount": 124,
      "cashOrBanlance": " ",
      "code": "55280e74-0e83-458a-8998-788cb5a9176d",
      "createTime": 1508251795107,
      "creatorId": -1,
      "defaultEntity": false,
      "details": [
        {
          "amount": 94,
          "code": "f9f4c8a8-ec93-4974-9c10-30c0c81be62d",
          "createTime": 1508251708535,
          "creatorId": -1,
          "defaultEntity": false,
          "id": 103,
          "number": 2,
          "objClass": "com.xdt.ums.shop.common.entity.DetailImpl",
          "productId": 3,
          "price": 32,
          "productName": "摩卡咖啡",
          "recordId": 102
        },
        {
          "amount": 30,
          "code": "b0c0d78f-3d38-4cd6-9902-7246cf47f980",
          "createTime": 1508251708535,
          "creatorId": -1,
          "defaultEntity": false,
          "id": 104,
          "number": 3,
          "objClass": "com.xdt.ums.shop.common.entity.DetailImpl",
          "productId": 3,
          "price": 10,
          "productName": "杯子蛋糕",
          "recordId": 102
        }
      ],
      "id": 102,
      "objClass": "com.xdt.ums.shop.common.entity.RecordImpl",
      "status": "success",
      "userId": 84,
      "userName": "test3"
    }
  ],
  "cartList": [
    {
      "amount": 56,
      "cashOrBanlance": " ",
      "code": "34c9829f-d57d-4e35-a8cb-51b861467b21",
      "createTime": 1508251634463,
      "creatorId": -1,
      "defaultEntity": false,
      "id": 99,
      "objClass": "com.xdt.ums.shop.common.entity.RecordImpl",
      "status": "success",
      "userId": 84,
      "userName": "test3"
    },
    {
      "amount": 56,
      "cashOrBanlance": " ",
      "code": "55280e74-0e83-458a-8998-788cb5a9176d",
      "createTime": 1508251795107,
      "creatorId": -1,
      "defaultEntity": false,
      "id": 102,
      "objClass": "com.xdt.ums.shop.common.entity.RecordImpl",
      "status": "success",
      "userId": 84,
      "userName": "test3"
    }
  ],
  "buyrecord": {
    "null": {
      "entityName": "null",
      "envData": {
        "endRow": -1,
        "language": "",
        "pageNo": -1,
        "pageSize": -1,
        "realTotalRows": -1,
        "responseStatus": "用户不存在",
        "startRow": -1,
        "totalPages": -1,
        "totalRows": -1,
        "userIp": "",
        "userName": ""
      },
      "success": false
    },
    "fail": {
      "envData": {
        "endRow": -1,
        "language": "",
        "pageNo": -1,
        "pageSize": -1,
        "realTotalRows": -1,
        "responseStatus": "余额不足",
        "startRow": -1,
        "totalPages": -1,
        "totalRows": -1,
        "userIp": "",
        "userName": ""
      },
      "success": false
    },
    "success": {
      "envData": {
        "endRow": -1,
        "language": "",
        "pageNo": -1,
        "pageSize": -1,
        "realTotalRows": -1,
        "responseStatus": "0",
        "startRow": -1,
        "totalPages": -1,
        "totalRows": -1,
        "userIp": "",
        "userName": ""
      },
      "success": true
    }
  }
}
